pyincus/__init__.py
pyincus/client.py
pyincus/config.py
pyincus/exceptions.py
pyincus/py.typed
pyincus/query.py
pyincus/status.py
pyincus/models/__init__.py
pyincus/models/general.py
pyincus/models/image.py
pyincus/models/instance.py
pyincus/models/network.py
pyincus/models/volume.py
pyincus-0.1.1.dist-info/METADATA
pyincus-0.1.1.dist-info/WHEEL
pyincus-0.1.1.dist-info/licenses/LICENSE
pyincus-0.1.1.dist-info/RECORD
