Metadata-Version: 2.4
Name: pyincus
Version: 0.1.1
Summary: SDK for interacting with incus
Project-URL: Source, https://github.com/EdmilsonRodrigues/pyincus
Project-URL: Homepage, https://pyincus.edmilsonrodrigues.com
Project-URL: Issues, https://github.com/EdmilsonRodrigues/pyincus/issues
Author-email: Edmilson Monteiro Rodrigues Neto <edmilson.rodriguesn38@gmail.com>
License-Expression: MPL-2.0
License-File: LICENSE
Classifier: Development Status :: 1 - Planning
Classifier: License :: OSI Approved :: Mozilla Public License 2.0 (MPL 2.0)
Classifier: Operating System :: POSIX :: Linux
Classifier: Programming Language :: Python :: 3.13
Requires-Python: >=3.13
Requires-Dist: aiohttp>=3.12.14
